code_guro/__init__.py
code_guro/analyzer.py
code_guro/cli.py
code_guro/cli_test.py
code_guro/config.py
code_guro/config_test.py
code_guro/conftest.py
code_guro/errors.py
code_guro/frameworks.py
code_guro/frameworks_test.py
code_guro/generator.py
code_guro/generator_test.py
code_guro/html_converter.py
code_guro/html_converter_test.py
code_guro/prompts.py
code_guro/repl.py
code_guro/utils.py
code_guro/utils_test.py
code_guro-0.4.2.dist-info/METADATA
code_guro-0.4.2.dist-info/WHEEL
code_guro-0.4.2.dist-info/entry_points.txt
code_guro-0.4.2.dist-info/top_level.txt
code_guro-0.4.2.dist-info/RECORD
