Metadata-Version: 2.4
Name: code-guro
Version: 0.4.2
Summary: A CLI tool to help non-technical product managers and AI-native builders understand codebases
Author-email: Nicola de Vera <nicola@example.com>
License: MIT
Project-URL: Homepage, https://github.com/nicoladevera/code-guro
Project-URL: Repository, https://github.com/nicoladevera/code-guro
Project-URL: Documentation, https://github.com/nicoladevera/code-guro#readme
Project-URL: Issues, https://github.com/nicoladevera/code-guro/issues
Keywords: cli,code-analysis,documentation,learning,ai
Classifier: Development Status :: 3 - Alpha
Classifier: Environment :: Console
Classifier: Intended Audience :: Developers
Classifier: License :: OSI Approved :: MIT License
Classifier: Operating System :: OS Independent
Classifier: Programming Language :: Python :: 3
Classifier: Programming Language :: Python :: 3.8
Classifier: Programming Language :: Python :: 3.9
Classifier: Programming Language :: Python :: 3.10
Classifier: Programming Language :: Python :: 3.11
Classifier: Programming Language :: Python :: 3.12
Classifier: Topic :: Documentation
Classifier: Topic :: Software Development :: Documentation
Requires-Python: >=3.8
Requires-Dist: anthropic>=0.18.0
Requires-Dist: click>=8.0
Requires-Dist: rich>=13.0
Requires-Dist: gitpython>=3.1
Requires-Dist: tiktoken>=0.5.0
Requires-Dist: markdown>=3.4
Provides-Extra: dev
Requires-Dist: pytest>=7.0; extra == "dev"
Requires-Dist: pytest-cov>=4.0; extra == "dev"
Requires-Dist: black>=23.0; extra == "dev"
Requires-Dist: ruff>=0.1.0; extra == "dev"
Requires-Dist: pre-commit>=3.0; extra == "dev"
Provides-Extra: enhanced
Requires-Dist: python-dotenv>=1.0; extra == "enhanced"
Requires-Dist: prompt_toolkit>=3.0; extra == "enhanced"
Requires-Dist: pygments>=2.15; extra == "enhanced"
Provides-Extra: all
Requires-Dist: code-guro[dev,enhanced]; extra == "all"
